{
  "lessons": [
    {
      "id": "MATH_MAT_001",
      "title": "Découvrir les nombres de 1 à 10",
      "discipline": "MATHEMATIQUES",
      "level": "MATERNELLE",
      "ageRange": "3-5 ans",
      "duration": 15,
      "objectives": [
        "Reconnaître les chiffres de 1 à 10",
        "Compter des objets jusqu'à 10",
        "Associer un nombre à une quantité"
      ],
      "content": {
        "introduction": "Bienvenue dans le monde magique des nombres! Aujourd'hui, nous allons apprendre à compter de 1 à 10 avec des objets colorés.",
        "sections": [
          {
            "title": "Les chiffres de 1 à 5",
            "text": "Regarde ces beaux ballons! Comptons-les ensemble: 1, 2, 3, 4, 5!",
            "visual": "ballons_colors.png",
            "interactive": true
          },
          {
            "title": "Les chiffres de 6 à 10",
            "text": "Maintenant, ajoutons d'autres ballons! 6, 7, 8, 9, 10! Bravo!",
            "visual": "plus_ballons.png",
            "interactive": true
          }
        ],
        "game": {
          "name": "Chasse aux Nombres",
          "description": "Trouve le bon nombre d'objets affichés à l'écran",
          "levels": 5,
          "reward": 20
        }
      },
      "prerequisites": [],
      "nextLessons": ["MATH_MAT_002"]
    },
    {
      "id": "FR_CP_001",
      "title": "Les voyelles magiques",
      "discipline": "FRANCAIS",
      "level": "CP_CE1",
      "ageRange": "6-7 ans",
      "duration": 20,
      "objectives": [
        "Identifier les 6 voyelles: A, E, I, O, U, Y",
        "Prononcer correctement chaque voyelle",
        "Écrire les voyelles en minuscule et majuscule"
      ],
      "content": {
        "introduction": "Découvre les lettres magiques qui font chanter les mots! Ce sont les voyelles.",
        "sections": [
          {
            "title": "A comme Afrique",
            "text": "Le A est la première lettre. Dis 'AAA' en ouvrant grand la bouche!",
            "visual": "lettre_A.png",
            "examples": ["Afrique", "Animal", "Ami"],
            "interactive": true
          },
          {
            "title": "E comme École",
            "text": "Le E sourit comme ça: ééé. Entends-tu le son?",
            "visual": "lettre_E.png",
            "examples": ["École", "Éléphant", "Étoile"],
            "interactive": true
          }
        ],
        "game": {
          "name": "La Rivière aux Voyelles",
          "description": "Attrape les bonnes voyelles qui flottent sur la rivière",
          "levels": 6,
          "reward": 25
        }
      },
      "prerequisites": [],
      "nextLessons": ["FR_CP_002"]
    },
    {
      "id": "CULT_CM2_001",
      "title": "Les grands empires africains",
      "discipline": "CULTURE_AFRICAINE",
      "level": "CM2",
      "ageRange": "10-11 ans",
      "duration": 30,
      "objectives": [
        "Connaître les trois grands empires: Ghana, Mali, Songhaï",
        "Comprendre leur organisation politique et économique",
        "Apprécier l'héritage culturel de ces empires"
      ],
      "content": {
        "introduction": "Il y a fort longtemps, avant la colonisation, l'Afrique avait de puissants royaumes. Partons à leur découverte!",
        "sections": [
          {
            "title": "L'Empire du Ghana (300-1200)",
            "text": "Le Ghana était célèbre pour son or et son commerce du sel. Son roi était très riche!",
            "visual": "carte_ghana.png",
            "keyFacts": [
              "Capitale: Koumbi Saleh",
              "Richesse principale: Or et sel",
              "Commerce transsaharien"
            ]
          },
          {
            "title": "L'Empire du Mali (1235-1600)",
            "text": "Mansa Moussa, roi du Mali, était l'homme le plus riche de l'histoire! Il a fait le pèlerinage à La Mecque avec tellement d'or qu'il a fait baisser sa valeur.",
            "visual": "mansa_moussa.png",
            "keyFacts": [
              "Fondateur: Soundiata Keïta",
              "Roi célèbre: Mansa Moussa",
              "Centre d'apprentissage: Tombouctou"
            ]
          },
          {
            "title": "L'Empire Songhaï (1464-1591)",
            "text": "Le plus grand empire d'Afrique de l'Ouest! Il contrôlait tout le commerce du fleuve Niger.",
            "visual": "carte_songhai.png",
            "keyFacts": [
              "Capitale: Gao",
              "Grand roi: Askia Mohammed",
              "Université de Sankoré à Tombouctou"
            ]
          }
        ],
        "game": {
          "name": "Voyage dans le Temps",
          "description": "Guide un marchand à travers les trois empires et apprends leur histoire",
          "levels": 3,
          "reward": 50
        }
      },
      "prerequisites": [],
      "nextLessons": ["CULT_CM2_002"]
    }
  ]
}
